procedure/__init__.py
procedure/context.py
procedure/procedure.py
procedure/procedure_failure.py
procedure/service.py
procedure-0.0.3.dist-info/LICENSE
procedure-0.0.3.dist-info/METADATA
procedure-0.0.3.dist-info/WHEEL
procedure-0.0.3.dist-info/top_level.txt
procedure-0.0.3.dist-info/RECORD
